tobii/__init__.py
tobii/engine.py
tobii/tobii.py
tobii/tobii_stream_engine.dll
tobii_python-0.1.1.dist-info/METADATA
tobii_python-0.1.1.dist-info/WHEEL
tobii_python-0.1.1.dist-info/RECORD
